Metadata-Version: 1.0
Name: fund-distributions
Version: 0.2
Summary: Gaussian  and Binomial distributions
Home-page: UNKNOWN
Author: Eduardo Chiarotti
Author-email: UNKNOWN
License: UNKNOWN
Platform: UNKNOWN
